[{"date":"2018-10-29","day":"Monday","hour":0,"congestion":5.89},{"date":"2018-10-29","day":"Monday","hour":1,"congestion":4.83},{"date":"2018-10-29","day":"Monday","hour":2,"congestion":4.89},{"date":"2018-10-29","day":"Monday","hour":3,"congestion":5.18},{"date":"2018-10-29","day":"Monday","hour":4,"congestion":5.14},{"date":"2018-10-29","day":"Monday","hour":5,"congestion":5.48},{"date":"2018-10-29","day":"Monday","hour":6,"congestion":12.13},{"date":"2018-10-29","day":"Monday","hour":7,"congestion":14.89},{"date":"2018-10-29","day":"Monday","hour":8,"congestion":17.92},{"date":"2018-10-29","day":"Monday","hour":9,"congestion":19.48},{"date":"2018-10-29","day":"Monday","hour":10,"congestion":21.25},{"date":"2018-10-29","day":"Monday","hour":11,"congestion":20.68},{"date":"2018-10-29","day":"Monday","hour":12,"congestion":21.76},{"date":"2018-10-29","day":"Monday","hour":13,"congestion":23.47},{"date":"2018-10-29","day":"Monday","hour":14,"congestion":24.35},{"date":"2018-10-29","day":"Monday","hour":15,"congestion":26.25},{"date":"2018-10-29","day":"Monday","hour":16,"congestion":23.18},{"date":"2018-10-29","day":"Monday","hour":17,"congestion":23.91},{"date":"2018-10-29","day":"Monday","hour":18,"congestion":28.23},{"date":"2018-10-29","day":"Monday","hour":19,"congestion":20.45},{"date":"2018-10-29","day":"Monday","hour":20,"congestion":16.95},{"date":"2018-10-29","day":"Monday","hour":21,"congestion":11.74},{"date":"2018-10-29","day":"Monday","hour":22,"congestion":8.74},{"date":"2018-10-29","day":"Monday","hour":23,"congestion":4.92},{"date":"2018-10-30","day":"Tuesday","hour":0,"congestion":4.98},{"date":"2018-10-30","day":"Tuesday","hour":1,"congestion":3.96},{"date":"2018-10-30","day":"Tuesday","hour":2,"congestion":4.65},{"date":"2018-10-30","day":"Tuesday","hour":3,"congestion":4.89},{"date":"2018-10-30","day":"Tuesday","hour":4,"congestion":5.97},{"date":"2018-10-30","day":"Tuesday","hour":5,"congestion":4.86},{"date":"2018-10-30","day":"Tuesday","hour":6,"congestion":8.12},{"date":"2018-10-30","day":"Tuesday","hour":7,"congestion":13.85},{"date":"2018-10-30","day":"Tuesday","hour":8,"congestion":18.67},{"date":"2018-10-30","day":"Tuesday","hour":9,"congestion":18.86},{"date":"2018-10-30","day":"Tuesday","hour":10,"congestion":24.1},{"date":"2018-10-30","day":"Tuesday","hour":11,"congestion":22.43},{"date":"2018-10-30","day":"Tuesday","hour":12,"congestion":21.92},{"date":"2018-10-30","day":"Tuesday","hour":13,"congestion":18.78},{"date":"2018-10-30","day":"Tuesday","hour":14,"congestion":24.21},{"date":"2018-10-30","day":"Tuesday","hour":15,"congestion":22.19},{"date":"2018-10-30","day":"Tuesday","hour":16,"congestion":22.95},{"date":"2018-10-30","day":"Tuesday","hour":17,"congestion":26.09},{"date":"2018-10-30","day":"Tuesday","hour":18,"congestion":21.54},{"date":"2018-10-30","day":"Tuesday","hour":19,"congestion":19.33},{"date":"2018-10-30","day":"Tuesday","hour":20,"congestion":15.07},{"date":"2018-10-30","day":"Tuesday","hour":21,"congestion":10.2},{"date":"2018-10-30","day":"Tuesday","hour":22,"congestion":7.29},{"date":"2018-10-30","day":"Tuesday","hour":23,"congestion":5.1},{"date":"2018-10-31","day":"Wednesday","hour":0,"congestion":4.77},{"date":"2018-10-31","day":"Wednesday","hour":1,"congestion":5.46},{"date":"2018-10-31","day":"Wednesday","hour":2,"congestion":5.29},{"date":"2018-10-31","day":"Wednesday","hour":3,"congestion":3.99},{"date":"2018-10-31","day":"Wednesday","hour":4,"congestion":4.03},{"date":"2018-10-31","day":"Wednesday","hour":5,"congestion":6.48},{"date":"2018-10-31","day":"Wednesday","hour":6,"congestion":11.65},{"date":"2018-10-31","day":"Wednesday","hour":7,"congestion":17.83},{"date":"2018-10-31","day":"Wednesday","hour":8,"congestion":16.17},{"date":"2018-10-31","day":"Wednesday","hour":9,"congestion":20.31},{"date":"2018-10-31","day":"Wednesday","hour":10,"congestion":19.81},{"date":"2018-10-31","day":"Wednesday","hour":11,"congestion":22.98},{"date":"2018-10-31","day":"Wednesday","hour":12,"congestion":19.01},{"date":"2018-10-31","day":"Wednesday","hour":13,"congestion":21.82},{"date":"2018-10-31","day":"Wednesday","hour":14,"congestion":22.24},{"date":"2018-10-31","day":"Wednesday","hour":15,"congestion":21.82},{"date":"2018-10-31","day":"Wednesday","hour":16,"congestion":22.9},{"date":"2018-10-31","day":"Wednesday","hour":17,"congestion":24.19},{"date":"2018-10-31","day":"Wednesday","hour":18,"congestion":24.52},{"date":"2018-10-31","day":"Wednesday","hour":19,"congestion":21.15},{"date":"2018-10-31","day":"Wednesday","hour":20,"congestion":14.33},{"date":"2018-10-31","day":"Wednesday","hour":21,"congestion":11.73},{"date":"2018-10-31","day":"Wednesday","hour":22,"congestion":8.97},{"date":"2018-10-31","day":"Wednesday","hour":23,"congestion":7.05},{"date":"2018-11-01","day":"Thursday","hour":0,"congestion":5.1},{"date":"2018-11-01","day":"Thursday","hour":1,"congestion":4.77},{"date":"2018-11-01","day":"Thursday","hour":2,"congestion":4.29},{"date":"2018-11-01","day":"Thursday","hour":3,"congestion":5.71},{"date":"2018-11-01","day":"Thursday","hour":4,"congestion":3.56},{"date":"2018-11-01","day":"Thursday","hour":5,"congestion":6.11},{"date":"2018-11-01","day":"Thursday","hour":6,"congestion":9.85},{"date":"2018-11-01","day":"Thursday","hour":7,"congestion":14.44},{"date":"2018-11-01","day":"Thursday","hour":8,"congestion":14.76},{"date":"2018-11-01","day":"Thursday","hour":9,"congestion":17.44},{"date":"2018-11-01","day":"Thursday","hour":10,"congestion":21.27},{"date":"2018-11-01","day":"Thursday","hour":11,"congestion":20.17},{"date":"2018-11-01","day":"Thursday","hour":12,"congestion":21.57},{"date":"2018-11-01","day":"Thursday","hour":13,"congestion":21.08},{"date":"2018-11-01","day":"Thursday","hour":14,"congestion":20.52},{"date":"2018-11-01","day":"Thursday","hour":15,"congestion":22.67},{"date":"2018-11-01","day":"Thursday","hour":16,"congestion":18.72},{"date":"2018-11-01","day":"Thursday","hour":17,"congestion":23.1},{"date":"2018-11-01","day":"Thursday","hour":18,"congestion":21.51},{"date":"2018-11-01","day":"Thursday","hour":19,"congestion":18.19},{"date":"2018-11-01","day":"Thursday","hour":20,"congestion":15.01},{"date":"2018-11-01","day":"Thursday","hour":21,"congestion":12.7},{"date":"2018-11-01","day":"Thursday","hour":22,"congestion":8.4},{"date":"2018-11-01","day":"Thursday","hour":23,"congestion":6.06},{"date":"2018-11-02","day":"Friday","hour":0,"congestion":5.15},{"date":"2018-11-02","day":"Friday","hour":1,"congestion":5.27},{"date":"2018-11-02","day":"Friday","hour":2,"congestion":4.28},{"date":"2018-11-02","day":"Friday","hour":3,"congestion":3.77},{"date":"2018-11-02","day":"Friday","hour":4,"congestion":5.69},{"date":"2018-11-02","day":"Friday","hour":5,"congestion":5.79},{"date":"2018-11-02","day":"Friday","hour":6,"congestion":11.1},{"date":"2018-11-02","day":"Friday","hour":7,"congestion":14.09},{"date":"2018-11-02","day":"Friday","hour":8,"congestion":17.89},{"date":"2018-11-02","day":"Friday","hour":9,"congestion":23.58},{"date":"2018-11-02","day":"Friday","hour":10,"congestion":25.14},{"date":"2018-11-02","day":"Friday","hour":11,"congestion":18.88},{"date":"2018-11-02","day":"Friday","hour":12,"congestion":13.43},{"date":"2018-11-02","day":"Friday","hour":13,"congestion":18.57},{"date":"2018-11-02","day":"Friday","hour":14,"congestion":24.62},{"date":"2018-11-02","day":"Friday","hour":15,"congestion":21.96},{"date":"2018-11-02","day":"Friday","hour":16,"congestion":23.06},{"date":"2018-11-02","day":"Friday","hour":17,"congestion":23.94},{"date":"2018-11-02","day":"Friday","hour":18,"congestion":24.88},{"date":"2018-11-02","day":"Friday","hour":19,"congestion":22.29},{"date":"2018-11-02","day":"Friday","hour":20,"congestion":14.71},{"date":"2018-11-02","day":"Friday","hour":21,"congestion":12.62},{"date":"2018-11-02","day":"Friday","hour":22,"congestion":8.18},{"date":"2018-11-02","day":"Friday","hour":23,"congestion":6.0},{"date":"2018-11-03","day":"Saturday","hour":0,"congestion":4.93},{"date":"2018-11-03","day":"Saturday","hour":1,"congestion":4.15},{"date":"2018-11-03","day":"Saturday","hour":2,"congestion":3.5},{"date":"2018-11-03","day":"Saturday","hour":3,"congestion":4.4},{"date":"2018-11-03","day":"Saturday","hour":4,"congestion":3.35},{"date":"2018-11-03","day":"Saturday","hour":5,"congestion":4.69},{"date":"2018-11-03","day":"Saturday","hour":6,"congestion":7.33},{"date":"2018-11-03","day":"Saturday","hour":7,"congestion":8.74},{"date":"2018-11-03","day":"Saturday","hour":8,"congestion":13.07},{"date":"2018-11-03","day":"Saturday","hour":9,"congestion":19.36},{"date":"2018-11-03","day":"Saturday","hour":10,"congestion":20.01},{"date":"2018-11-03","day":"Saturday","hour":11,"congestion":20.19},{"date":"2018-11-03","day":"Saturday","hour":12,"congestion":20.27},{"date":"2018-11-03","day":"Saturday","hour":13,"congestion":23.65},{"date":"2018-11-03","day":"Saturday","hour":14,"congestion":20.05},{"date":"2018-11-03","day":"Saturday","hour":15,"congestion":20.08},{"date":"2018-11-03","day":"Saturday","hour":16,"congestion":21.76},{"date":"2018-11-03","day":"Saturday","hour":17,"congestion":23.31},{"date":"2018-11-03","day":"Saturday","hour":18,"congestion":18.71},{"date":"2018-11-03","day":"Saturday","hour":19,"congestion":22.52},{"date":"2018-11-03","day":"Saturday","hour":20,"congestion":17.14},{"date":"2018-11-03","day":"Saturday","hour":21,"congestion":13.59},{"date":"2018-11-03","day":"Saturday","hour":22,"congestion":9.22},{"date":"2018-11-03","day":"Saturday","hour":23,"congestion":4.96},{"date":"2018-11-04","day":"Sunday","hour":0,"congestion":4.86},{"date":"2018-11-04","day":"Sunday","hour":1,"congestion":3.85},{"date":"2018-11-04","day":"Sunday","hour":3,"congestion":2.49},{"date":"2018-11-04","day":"Sunday","hour":4,"congestion":4.32},{"date":"2018-11-04","day":"Sunday","hour":5,"congestion":4.76},{"date":"2018-11-04","day":"Sunday","hour":6,"congestion":6.55},{"date":"2018-11-04","day":"Sunday","hour":7,"congestion":7.61},{"date":"2018-11-04","day":"Sunday","hour":8,"congestion":10.64},{"date":"2018-11-04","day":"Sunday","hour":9,"congestion":11.23},{"date":"2018-11-04","day":"Sunday","hour":10,"congestion":13.3},{"date":"2018-11-04","day":"Sunday","hour":11,"congestion":11.57},{"date":"2018-11-04","day":"Sunday","hour":12,"congestion":11.09},{"date":"2018-11-04","day":"Sunday","hour":13,"congestion":11.79},{"date":"2018-11-04","day":"Sunday","hour":14,"congestion":14.79},{"date":"2018-11-04","day":"Sunday","hour":15,"congestion":14.65},{"date":"2018-11-04","day":"Sunday","hour":16,"congestion":14.03},{"date":"2018-11-04","day":"Sunday","hour":17,"congestion":16.37},{"date":"2018-11-04","day":"Sunday","hour":18,"congestion":16.19},{"date":"2018-11-04","day":"Sunday","hour":19,"congestion":12.74},{"date":"2018-11-04","day":"Sunday","hour":20,"congestion":12.8},{"date":"2018-11-04","day":"Sunday","hour":21,"congestion":10.45},{"date":"2018-11-04","day":"Sunday","hour":22,"congestion":8.09},{"date":"2018-11-04","day":"Sunday","hour":23,"congestion":3.89}]